datawrapper/__init__.py
datawrapper/__main__.py
datawrapper/chart_factory.py
datawrapper/exceptions.py
datawrapper/flags.py
datawrapper/py.typed
datawrapper/charts/__init__.py
datawrapper/charts/area.py
datawrapper/charts/arrow.py
datawrapper/charts/bar.py
datawrapper/charts/base.py
datawrapper/charts/column.py
datawrapper/charts/line.py
datawrapper/charts/multiple_column.py
datawrapper/charts/scatter.py
datawrapper/charts/stacked_bar.py
datawrapper/charts/enums/__init__.py
datawrapper/charts/enums/annos.py
datawrapper/charts/enums/date_format.py
datawrapper/charts/enums/grid_display.py
datawrapper/charts/enums/grid_label.py
datawrapper/charts/enums/interpolation.py
datawrapper/charts/enums/line_dash.py
datawrapper/charts/enums/line_width.py
datawrapper/charts/enums/number_divisor.py
datawrapper/charts/enums/number_format.py
datawrapper/charts/enums/plot_height.py
datawrapper/charts/enums/replace_flags.py
datawrapper/charts/enums/scatter_shape.py
datawrapper/charts/enums/symbol_shape.py
datawrapper/charts/enums/text_align.py
datawrapper/charts/enums/value_label.py
datawrapper/charts/models/__init__.py
datawrapper/charts/models/api_sections.py
datawrapper/charts/models/mixins.py
datawrapper/charts/models/range_annotations.py
datawrapper/charts/models/text_annotations.py
datawrapper/charts/models/transforms.py
datawrapper/charts/serializers/__init__.py
datawrapper/charts/serializers/base.py
datawrapper/charts/serializers/color_category.py
datawrapper/charts/serializers/custom_range.py
datawrapper/charts/serializers/custom_ticks.py
datawrapper/charts/serializers/model_list.py
datawrapper/charts/serializers/negative_color.py
datawrapper/charts/serializers/plot_height.py
datawrapper/charts/serializers/replace_flags.py
datawrapper/charts/serializers/value_labels.py
datawrapper-2.0.14.dist-info/licenses/LICENSE
datawrapper-2.0.14.dist-info/METADATA
datawrapper-2.0.14.dist-info/WHEEL
datawrapper-2.0.14.dist-info/top_level.txt
datawrapper-2.0.14.dist-info/RECORD
