Metadata-Version: 2.4
Name: datawrapper
Version: 2.0.14
Summary: A lightweight Python wrapper for the Datawrapper API
Author-email: checkos <chekos@tacosdedatos.com>, Ben Welsh <b@palewi.re>
License: MIT
Project-URL: Documentation, https://github.com/chekos/datawrapper
Project-URL: Maintainer, https://github.com/chekos/
Project-URL: Source, https://github.com/chekos/datawrapper
Project-URL: Issues, https://github.com/chekos/datawrapper/issues/
Classifier: Development Status :: 5 - Production/Stable
Classifier: Programming Language :: Python
Classifier: Programming Language :: Python :: 3
Classifier: Programming Language :: Python :: 3.10
Classifier: Programming Language :: Python :: 3.11
Classifier: Programming Language :: Python :: 3.12
Classifier: Programming Language :: Python :: 3.13
Classifier: License :: OSI Approved :: MIT License
Classifier: Intended Audience :: Developers
Classifier: Operating System :: OS Independent
Classifier: Topic :: Software Development :: Libraries :: Python Modules
Classifier: Typing :: Typed
Requires-Python: >=3.10.0
License-File: LICENSE
Requires-Dist: exceptiongroup; python_version < "3.11"
Requires-Dist: importlib_metadata
Requires-Dist: rich
Requires-Dist: requests
Requires-Dist: pandas
Requires-Dist: pydantic
Requires-Dist: ipython
Provides-Extra: dev
Requires-Dist: pre-commit; extra == "dev"
Requires-Dist: setuptools-scm; extra == "dev"
Provides-Extra: test
Requires-Dist: pytest; extra == "test"
Requires-Dist: pytest-cov; extra == "test"
Requires-Dist: pytest-mock; extra == "test"
Requires-Dist: pytest-asyncio; extra == "test"
Requires-Dist: pytest-timeout; extra == "test"
Requires-Dist: pytest-xdist; extra == "test"
Requires-Dist: pytest-env; extra == "test"
Requires-Dist: factory-boy; extra == "test"
Requires-Dist: faker; extra == "test"
Requires-Dist: responses; extra == "test"
Requires-Dist: freezegun; extra == "test"
Provides-Extra: docs
Requires-Dist: sphinx; extra == "docs"
Requires-Dist: sphinx-autobuild; extra == "docs"
Requires-Dist: myst-parser; extra == "docs"
Requires-Dist: sphinx_rtd_theme; extra == "docs"
Provides-Extra: mypy
Requires-Dist: mypy; extra == "mypy"
Requires-Dist: types-requests; extra == "mypy"
Requires-Dist: types-docutils; extra == "mypy"
Requires-Dist: pydantic-settings; extra == "mypy"
Dynamic: license-file
